MANIFEST.in
README.md
README_EN.md
requirements.txt
setup.py
botank/__init__.py
botank/__main__.py
botank/copypaste_responder.py
botank/phrases.py
botank/request_generator.py
botank/shooter.py
botank/shooter_result.py
botank/simple_responders.py
botank.egg-info/PKG-INFO
botank.egg-info/SOURCES.txt
botank.egg-info/dependency_links.txt
botank.egg-info/requires.txt
botank.egg-info/top_level.txt