Metadata-Version: 2.1
Name: botank
Version: 0.0.5
Summary: A library for automated testing of Alice skills
Home-page: https://github.com/avidale/botank
Author: David Dale
Author-email: dale.david@mail.ru
License: MIT
Platform: UNKNOWN
Classifier: Development Status :: 3 - Alpha
Classifier: Programming Language :: Python :: 3
Classifier: License :: OSI Approved :: MIT License
Classifier: Operating System :: OS Independent
